{
  "$schema": "https://schemas.wp.org/trunk/block.json",
  "apiVersion": 3,
  "name": "air-light/latest-articles",
  "version": "1.0.0",
  "title": "Latest articles",
  "category": "air-light",
  "icon": "grid-view",
  "description": "Show latest articles in a grid.",
  "example": {},
  "supports": {
    "html": true,
    "align": false
  },
  "textdomain": "air-light",
  "editorScript": "file:./index.js",
  "editorStyle": "file:./index.css",
  "style": "file:./style-index.css",
  "render": "file:./render.php",
  "viewScript": "file:./view.js",
  "attributes": {
    "preview": {
      "type": "boolean",
      "default": false
    }
  }
}